yaarg/__init__.py
yaarg/markdown.py
yaarg/mkdocs.py
yaarg/resolver.py
yaarg/generators/__init__.py
yaarg/generators/base.py
yaarg/generators/jsdoc.py
yaarg/generators/parso.py
mkdocs_yaarg_plugin-0.0.1a5.dist-info/METADATA
mkdocs_yaarg_plugin-0.0.1a5.dist-info/WHEEL
mkdocs_yaarg_plugin-0.0.1a5.dist-info/entry_points.txt
mkdocs_yaarg_plugin-0.0.1a5.dist-info/top_level.txt
mkdocs_yaarg_plugin-0.0.1a5.dist-info/RECORD
